dailyrun/__init__.py
dailyrun/dailyrun.py
dailyrun-0.0.1.dist-info/LICENSE
dailyrun-0.0.1.dist-info/METADATA
dailyrun-0.0.1.dist-info/WHEEL
dailyrun-0.0.1.dist-info/top_level.txt
dailyrun-0.0.1.dist-info/RECORD
